{
    "uuid": "a8024310-d970-4495-9456-65656f8ff6e6",
    "submitted": "2026-04-13T16:44:18",
    "filetype": "Gizmo",
    "filename": "1",
    "author": "Yadnyesh",
    "version": 2,
    "sub_category": "Draw",
    "render": "CPU",
    "nuke_version": "Nuke13-",
    "description": "2",
    "tagline": "2",
    "extra_docs": [
        "H:/Gamut/Projects/node_vault/test.doc",
        "H:/Gamut/Projects/node_vault/test.doc"
    ],
    "repo_link": "2",
    "issues_link": "2",
    "website": "22",
    "extra_link": "2",
    "attached_images": [
        "C:/Users/Yadnyesh/Pictures/1.png"
    ],
    "attached_video": []
}